{"_v":"2026-07-16T16:47:37.500Z","user":{"iidx_id":"67862017","dj_name":"LISASU","star":12.61,"ereter_star":12.121620077398592,"sp_rank":12,"dp_rank":12,"date":"2026-07-16T16:47:16.628931+00:00","native_star":10.35,"sp_cpi":null,"sp_star":null},"radars":[{"iidx_id":"67862017","play_style":0,"notes":113.06,"peak":116.22,"charge":56.12,"chord":108.73,"scratch":76.45,"soft":26.43,"date":"2026-07-16T16:47:16.758749+00:00"},{"iidx_id":"67862017","play_style":1,"notes":163.93,"peak":160.32,"charge":173.8,"chord":177.17,"scratch":166.67,"soft":156.3,"date":"2026-07-16T16:47:16.815963+00:00"}],"osPattern":[],"persona":null,"spPersona":null,"dp":[],"sp":[]}