{"_v":"2026-07-17T07:41:45.174Z","user":{"iidx_id":"91151737","dj_name":"MOCHA","star":2.67,"ereter_star":null,"sp_rank":11,"dp_rank":null,"date":"2026-07-17T07:41:26.509278+00:00","native_star":2.65,"sp_cpi":null,"sp_star":null},"radars":[{"iidx_id":"91151737","play_style":0,"notes":137.46,"peak":139.12,"charge":146.3,"chord":156.17,"scratch":154.32,"soft":126.35,"date":"2026-05-30T13:04:30.947719+00:00"},{"iidx_id":"91151737","play_style":1,"notes":0,"peak":0,"charge":0,"chord":0,"scratch":0,"soft":0,"date":"2026-05-30T13:04:31.030222+00:00"}],"osPattern":[],"persona":{"head":"ьзАыаеэШХ","oneLiner":"ыВЬэГА┬╖эК╕ыж┤┬╖ъ│ДыЛи ъ░ХьаР, ьХ╜ьаРьЭА ьЖМэФДыЮА┬╖ь░иьзА.","prose":"ыВЬэГАьЩА эК╕ыж┤ьЧР ъ░ХэХЬ эБ┤ыжмьЦ┤(ыЮиэФД) ьзАэЦе эФМыаИьЭ┤ьЦ┤. ьЦСьЖР ъ│ДыЛи ьЭСьЪй(эХЬьЖР┬╖ьМНъ│ДыЛиыеШ) ы░░ь╣ШыПД ьЮШ ьЖМэЩФэХЬыЛд. ъ░ЬьЭ╕ь░иьЧРьДЬыКФ ь░иьзАьЩА ы│АьЖНьЭ┤ ьХ╜эХШыЛд.","report":"ЁЯОп ъ│б ьЬаэШХ (ы│╕ьЭ╕ эПЙъ╖а ыМАы╣Д)\n- ъ░ХэХи: ыВЬэГА(+1.8), эК╕ыж┤(+1.1), ъ│ДыЛи(+1.0) тАФ ьзАыае ъ│ДьЧ┤ ъ│аые╕ ъ░ХьД╕\n- ьХ╜эХи: ыЪЬыа╖эХЬ ьХ╜ьаР ьЬаэШХ ьЧЖьЭМ\n- ы░░ь╣Ш ь╢Х: ьЦСьЖРъ│ДыЛи ьаДы░ШьаБьЬ╝ыбЬ ъ░ХэХи(+2.7), ьШдые╕ыВШьДа ъ░ХэХи(+6.7), ьЩ╝ыВШьДа ъ░ХэХи(+4.7)\n\nЁЯО▓ ъ░ЬьЭ╕ь░и\n- ь░иьзА -1.6 ьХ╜эХи / ьКдэБм +0.1 ы│┤эЖ╡ / ьЖМэФДыЮА -4.9 ьХХыПДьаБ ьХ╜ьаР\n- ьКдэБм ьГБьД╕: ъ▓мьаЬ +0.4 ы│┤эЖ╡ ┬╖ ыбдьЖНыПД ьаАьЖН -0.8/ьдСьЖН +1.2/ъ│аьЖН +1.2\n\nтЪб ьЖНыПД\n- ым╝ыжм ыЕ╕эК╕ьЖНыПД(ъ▒┤ы░Ш): ьаАьЖН -0.5(ьКдэК╕ыж╝ -0.8/эК╕ыж┤ -0.7/ьЧ░эГА -0.0) ┬╖ ьдСьЖН +0.3(ьКдэК╕ыж╝ +0.1/эК╕ыж┤ +0.2/ьЧ░эГА +0.6) ┬╖ ъ│аьЖН +0.6(ьКдэК╕ыж╝ +1.2/эК╕ыж┤ +0.1) ┬╖ ь┤Иъ│аьЖН +1.7(ьКдэК╕ыж╝ +2.1/эК╕ыж┤ +1.3)\n- эСЬъ╕░ BPM: ь╡Ьъ░Х 150ыМА(+0.5) / ь╡ЬьХ╜ 120ыМА(-0.6)\n\nЁЯЫа ым┤ыжмы░░ь╣Ш: ьКдэБмым┤ыжм +0.3 / ым┤ыжмэК╕ыж┤ -0.0\n\nтЬЛ ьЖРы│Д ь░иьЭ┤: ьвМьЪ░ ъ╖аэШХ\n- ьД╕ы╢А(+ьЩ╝ьЖР/тИТьШдые╕ьЖР): ыПЩьЛЬь╣Шъ╕░ -0.4 ┬╖ ьЧ░эГА +0.3 ┬╖ ыВЬэГА +0.3 ┬╖ ьКдэБм +0.3 ┬╖ эК╕ыж┤ +0.1 ┬╖ ьИЬъ░Ды░АыПД -0.1 ┬╖ ь░иьзА -0.1 ┬╖ ъ│ДыЛи +0.0 ┬╖ ым╝ыЯЙ -0.0 ┬╖ ьЖМэФДыЮА +0.0\n\nЁЯУЭ ьЪФьХ╜\n- \"ыВЬэГАьЩА эК╕ыж┤ьЧР ъ░ХэХЬ эБ┤ыжмьЦ┤(ыЮиэФД) ьзАэЦе эФМыаИьЭ┤ьЦ┤. ьЦСьЖР ъ│ДыЛи ьЭСьЪй(эХЬьЖР┬╖ьМНъ│ДыЛиыеШ) ы░░ь╣ШыПД ьЮШ ьЖМэЩФэХЬыЛд. ъ░ЬьЭ╕ь░иьЧРьДЬыКФ ь░иьзАьЩА ы│АьЖНьЭ┤ ьХ╜эХШыЛд.\"\n- ьКдэГАьЭ╝: ыПЩыаИы▓и ыМАы╣Д rate ыВоьЭМ тАФ ьКдь╜ФьЦ┤ы│┤ыЛд эБ┤ыжмьЦ┤(ыЮиэФД) ьзАэЦе\n- ЁЯП╖ #ыВЬэГАтЖС #эК╕ыж┤тЖС #ъ│ДыЛитЖС #ьЖМэФДыЮАтЖУ #ь░иьзАтЖУ #ьЦСьЖРъ│ДыЛитЖС #ьШдые╕ыВШьДатЖС #ьЩ╝ыВШьДатЖС #ыЮиэФДьзАэЦе","tags":["#ыВЬэГАтЖС","#эК╕ыж┤тЖС","#ъ│ДыЛитЖС","#ьЖМэФДыЮАтЖУ","#ь░иьзАтЖУ","#ьЦСьЖРъ│ДыЛитЖС","#ьШдые╕ыВШьДатЖС","#ьЩ╝ыВШьДатЖС","#ыЮиэФДьзАэЦе"],"nCharts":138,"_v":"2026-07-17T11:10:58.957Z","i18n":{"ja":{"head":"хЬ░хКЫхЮЛ","report":"ЁЯОп цЫ▓уБох▒ЮцАз (цЬмф║║х╣│хЭЗцпФ)\n- х╛ЧцДП: ф╣▒цЙУ(+1.8), уГИуГкуГл(+1.1), щЪОцо╡(+1.0) тАФ хЬ░хКЫч│╗уБМч╖ПуБШуБжх╝╖уБД\n- шЛжцЙЛ: щЪЫчлЛуБгуБЯшЛжцЙЛуВ┐уВдуГЧуБкуБЧ\n- щЕНч╜оуБош╗╕: ф╕бцЙЛщЪОцо╡уБМхЕиф╜УчЪДуБлх╛ЧцДП(+2.7), хП│шЮ║цЧЛуБМх╛ЧцДП(+6.7), х╖жшЮ║цЧЛуБМх╛ЧцДП(+4.7)\n\nЁЯО▓ хАЛф║║х╖о\n- уГБуГгуГ╝уВ╕ -1.6 шЛжцЙЛ / чЪ┐ +0.1 цЩощАЪ / уВ╜уГХуГйуГ│ -4.9 хЬзхАТчЪДуБкх╝▒чВ╣\n- чЪ┐уБошй│ч┤░: чЪ┐ч╡буБ┐ +0.4 цЩощАЪ ┬╖ уГнуГ╝уГлщАЯх║ж ф╜ОщАЯ -0.8/ф╕нщАЯ +1.2/щлШщАЯ +1.2\n\nтЪб щАЯх║ж\n- чЙйчРЖуГОуГ╝уГДщАЯх║ж(щН╡чЫд): ф╜ОщАЯ -0.5(уВ╣уГИуГкуГ╝уГа -0.8/уГИуГкуГл -0.7/щАгцЙУ -0.0) ┬╖ ф╕нщАЯ +0.3(уВ╣уГИуГкуГ╝уГа +0.1/уГИуГкуГл +0.2/щАгцЙУ +0.6) ┬╖ щлШщАЯ +0.6(уВ╣уГИуГкуГ╝уГа +1.2/уГИуГкуГл +0.1) ┬╖ ш╢ЕщлШщАЯ +1.7(уВ╣уГИуГкуГ╝уГа +2.1/уГИуГкуГл +1.3)\n- шбишиШBPM: цЬАх╝╖ 150х╕п(+0.5) / цЬАх╝▒ 120х╕п(-0.6)\n\nЁЯЫа чДбчРЖщЕНч╜о: чДбчРЖчЪ┐ +0.3 / чДбчРЖуГИуГкуГл -0.0\n\nтЬЛ цЙЛхИеуБох╖о: х╖жхП│уГРуГйуГ│уВ╣\n- шй│ч┤░(+х╖жцЙЛ/тИТхП│цЙЛ): хРМцЩВцК╝уБЧ -0.4 ┬╖ щАгцЙУ +0.3 ┬╖ ф╣▒цЙУ +0.3 ┬╖ чЪ┐ +0.3 ┬╖ уГИуГкуГл +0.1 ┬╖ чЮмщЦУхпЖх║ж -0.1 ┬╖ уГБуГгуГ╝уВ╕ -0.1 ┬╖ щЪОцо╡ +0.0 ┬╖ чЙйщЗП -0.0 ┬╖ уВ╜уГХуГйуГ│ +0.0\n\nЁЯУЭ уБ╛уБиуВБ\n- \"ф╣▒цЙУуГ╗уГИуГкуГлуГ╗щЪОцо╡уБМх╝╖уБ┐уАБх╝▒чВ╣уБпуВ╜уГХуГйуГ│уГ╗уГБуГгуГ╝уВ╕уАВ\"\n- уВ╣уВ┐уВдуГл: хРМуГмуГЩуГлцпФуБзуГмуГ╝уГИф╜ОуВБ тАФ уВ╣уВ│уВвуВИуВКуВпуГкуВв(уГйуГ│уГЧ)щЗНшжЦ\n- ЁЯП╖ #ф╣▒цЙУтЖС #уГИуГкуГлтЖС #щЪОцо╡тЖС #уВ╜уГХуГйуГ│тЖУ #уГБуГгуГ╝уВ╕тЖУ #ф╕бцЙЛщЪОцо╡тЖС #хП│шЮ║цЧЛтЖС #х╖жшЮ║цЧЛтЖС #уВпуГкуВвщЗНшжЦ"},"en":{"head":"reader","report":"ЁЯОп Chart Types (vs personal avg)\n- Strong: Stream(+1.8), Trills(+1.1), Stairs(+1.0) тАФ solid across reading-skill types\n- Weak: no distinct weaknesses\n- Layout: both-hand stairs overall strong(+2.7), Right Spiral strong(+6.7), Left Spiral strong(+4.7)\n\nЁЯО▓ Individual Factors\n- Charge -1.6 weak / Scratch +0.1 average / Soflan -4.9 dominant weakness\n- Scratch detail: Scratch-Key +0.4 average ┬╖ Roll speed Low -0.8/Mid +1.2/High +1.2\n\nтЪб Speed\n- Physical note speed: Low -0.5(Stream -0.8/Trill -0.7/Jack -0.0) ┬╖ Mid +0.3(Stream +0.1/Trill +0.2/Jack +0.6) ┬╖ High +0.6(Stream +1.2/Trill +0.1) ┬╖ Hyper +1.7(Stream +2.1/Trill +1.3)\n- Scroll BPM: best 150s(+0.5) / worst 120s(-0.6)\n\nЁЯЫа Awkward layouts: Awkward Scratch +0.3 / Awkward Trill -0.0\n\nтЬЛ Hand dominance: balanced\n- Detail (+L / тИТR): Chords -0.4 ┬╖ Jacks +0.3 ┬╖ Stream +0.3 ┬╖ Scratch +0.3 ┬╖ Trills +0.1 ┬╖ Peak -0.1 ┬╖ Charge -0.1 ┬╖ Stairs +0.0 ┬╖ Density -0.0 ┬╖ Soflan +0.0\n\nЁЯУЭ Summary\n- \"Stream, Trills, Stairs strong, weak: Soflan, Charge.\"\n- Style: lower rate for the level тАФ clear(lamp)-oriented over score\n- ЁЯП╖ #StreamтЖС #TrillsтЖС #StairsтЖС #SoflanтЖУ #ChargeтЖУ #Both-handstairsтЖС #RightSpiralтЖС #LeftSpiralтЖС #Clear-oriented"}}},"spPersona":null,"dp":[{"song_id":6,"diff":3,"lamp":3,"ex_score":0,"played_version":33,"date":"2026-05-30T13:04:30+00:00"},{"song_id":14,"diff":3,"lamp":2,"ex_score":0,"played_version":33,"date":"2026-05-30T13:04:30+00:00"},{"song_id":15,"diff":3,"lamp":3,"ex_score":0,"played_version":33,"date":"2026-05-30T13:04:30+00:00"},{"song_id":18,"diff":3,"lamp":3,"ex_score":0,"played_version":33,"date":"2026-05-30T13:04:30+00:00"},{"song_id":127,"diff":2,"lamp":4,"ex_score":0,"played_version":33,"date":"2026-05-30T13:04:30+00:00"},{"song_id":129,"diff":3,"lamp":4,"ex_score":0,"played_version":33,"date":"2026-05-30T13:04:30+00:00"},{"song_id":131,"diff":3,"lamp":3,"ex_score":0,"played_version":33,"date":"2026-05-30T13:04:30+00:00"},{"song_id":139,"diff":3,"lamp":3,"ex_score":0,"played_version":33,"date":"2026-05-30T13:04:30+00:00"},{"song_id":165,"diff":3,"lamp":3,"ex_score":0,"played_version":33,"date":"2026-05-30T13:04:30+00:00"},{"song_id":173,"diff":3,"lamp":3,"ex_score":0,"played_version":33,"date":"2026-05-30T13:04:30+00:00"},{"song_id":176,"diff":3,"lamp":3,"ex_score":0,"played_version":33,"date":"2026-05-30T13:04:30+00:00"},{"song_id":184,"diff":3,"lamp":3,"ex_score":0,"played_version":33,"date":"2026-05-30T13:04:30+00:00"},{"song_id":186,"diff":3,"lamp":3,"ex_score":0,"played_version":33,"date":"2026-05-30T13:04:30+00:00"},{"song_id":200,"diff":3,"lamp":3,"ex_score":0,"played_version":33,"date":"2026-05-30T13:04:30+00:00"},{"song_id":214,"diff":3,"lamp":3,"ex_score":0,"played_version":33,"date":"2026-05-30T13:04:30+00:00"},{"song_id":225,"diff":3,"lamp":1,"ex_score":0,"played_version":33,"date":"2026-05-30T13:04:30+00:00"},{"song_id":232,"diff":3,"lamp":3,"ex_score":0,"played_version":33,"date":"2026-05-30T13:04:30+00:00"},{"song_id":242,"diff":3,"lamp":3,"ex_score":0,"played_version":33,"date":"2026-05-30T13:04:30+00:00"},{"song_id":258,"diff":3,"lamp":3,"ex_score":0,"played_version":33,"date":"2026-05-30T13:04:30+00:00"},{"song_id":260,"diff":3,"lamp":3,"ex_score":0,"played_version":33,"date":"2026-05-30T13:04:30+00:00"},{"song_id":263,"diff":3,"lamp":3,"ex_score":0,"played_version":33,"date":"2026-05-30T13:04:30+00:00"},{"song_id":264,"diff":3,"lamp":3,"ex_score":0,"played_version":33,"date":"2026-05-30T13:04:30+00:00"},{"song_id":269,"diff":3,"lamp":3,"ex_score":0,"played_version":33,"date":"2026-05-30T13:04:30+00:00"},{"song_id":277,"diff":3,"lamp":3,"ex_score":0,"played_version":33,"date":"2026-05-30T13:04:30+00:00"},{"song_id":282,"diff":3,"lamp":3,"ex_score":0,"played_version":33,"date":"2026-05-30T13:04:30+00:00"},{"song_id":285,"diff":3,"lamp":3,"ex_score":0,"played_version":33,"date":"2026-05-30T13:04:30+00:00"},{"song_id":291,"diff":3,"lamp":3,"ex_score":0,"played_version":33,"date":"2026-05-30T13:04:30+00:00"},{"song_id":293,"diff":3,"lamp":3,"ex_score":0,"played_version":33,"date":"2026-05-30T13:04:30+00:00"},{"song_id":306,"diff":3,"lamp":3,"ex_score":0,"played_version":33,"date":"2026-05-30T13:04:30+00:00"},{"song_id":307,"diff":3,"lamp":3,"ex_score":0,"played_version":33,"date":"2026-05-30T13:04:30+00:00"},{"song_id":316,"diff":3,"lamp":3,"ex_score":0,"played_version":33,"date":"2026-05-30T13:04:30+00:00"},{"song_id":320,"diff":3,"lamp":1,"ex_score":0,"played_version":33,"date":"2026-05-30T13:04:30+00:00"},{"song_id":325,"diff":3,"lamp":3,"ex_score":0,"played_version":33,"date":"2026-05-30T13:04:30+00:00"},{"song_id":344,"diff":3,"lamp":3,"ex_score":0,"played_version":33,"date":"2026-05-30T13:04:30+00:00"},{"song_id":345,"diff":3,"lamp":3,"ex_score":0,"played_version":33,"date":"2026-05-30T13:04:30+00:00"},{"song_id":350,"diff":3,"lamp":3,"ex_score":0,"played_version":33,"date":"2026-05-30T13:04:30+00:00"},{"song_id":376,"diff":3,"lamp":3,"ex_score":0,"played_version":33,"date":"2026-05-30T13:04:30+00:00"},{"song_id":377,"diff":3,"lamp":3,"ex_score":0,"played_version":33,"date":"2026-05-30T13:04:30+00:00"},{"song_id":378,"diff":3,"lamp":4,"ex_score":0,"played_version":33,"date":"2026-05-30T13:04:30+00:00"},{"song_id":384,"diff":3,"lamp":3,"ex_score":0,"played_version":33,"date":"2026-05-30T13:04:30+00:00"},{"song_id":394,"diff":3,"lamp":1,"ex_score":0,"played_version":33,"date":"2026-05-30T13:04:30+00:00"},{"song_id":416,"diff":3,"lamp":4,"ex_score":0,"played_version":33,"date":"2026-05-30T13:04:30+00:00"},{"song_id":417,"diff":3,"lamp":3,"ex_score":0,"played_version":33,"date":"2026-05-30T13:04:30+00:00"},{"song_id":422,"diff":3,"lamp":3,"ex_score":0,"played_version":33,"date":"2026-05-30T13:04:30+00:00"},{"song_id":431,"diff":3,"lamp":4,"ex_score":0,"played_version":33,"date":"2026-05-30T13:04:30+00:00"},{"song_id":437,"diff":3,"lamp":3,"ex_score":0,"played_version":33,"date":"2026-05-30T13:04:30+00:00"},{"song_id":445,"diff":3,"lamp":3,"ex_score":0,"played_version":33,"date":"2026-05-30T13:04:30+00:00"},{"song_id":447,"diff":3,"lamp":3,"ex_score":0,"played_version":33,"date":"2026-05-30T13:04:30+00:00"},{"song_id":449,"diff":3,"lamp":3,"ex_score":0,"played_version":33,"date":"2026-05-30T13:04:30+00:00"},{"song_id":451,"diff":3,"lamp":3,"ex_score":0,"played_version":33,"date":"2026-05-30T13:04:30+00:00"},{"song_id":453,"diff":3,"lamp":3,"ex_score":0,"played_version":33,"date":"2026-05-30T13:04:30+00:00"},{"song_id":458,"diff":3,"lamp":3,"ex_score":0,"played_version":33,"date":"2026-05-30T13:04:30+00:00"},{"song_id":464,"diff":3,"lamp":3,"ex_score":0,"played_version":33,"date":"2026-05-30T13:04:30+00:00"},{"song_id":502,"diff":3,"lamp":3,"ex_score":0,"played_version":33,"date":"2026-05-30T13:04:30+00:00"},{"song_id":506,"diff":3,"lamp":3,"ex_score":0,"played_version":33,"date":"2026-05-30T13:04:30+00:00"},{"song_id":512,"diff":3,"lamp":3,"ex_score":0,"played_version":33,"date":"2026-05-30T13:04:30+00:00"},{"song_id":513,"diff":3,"lamp":3,"ex_score":0,"played_version":33,"date":"2026-05-30T13:04:30+00:00"},{"song_id":524,"diff":3,"lamp":1,"ex_score":0,"played_version":33,"date":"2026-05-30T13:04:30+00:00"},{"song_id":538,"diff":3,"lamp":2,"ex_score":0,"played_version":33,"date":"2026-05-30T13:04:30+00:00"},{"song_id":545,"diff":3,"lamp":3,"ex_score":0,"played_version":33,"date":"2026-05-30T13:04:30+00:00"},{"song_id":550,"diff":3,"lamp":3,"ex_score":0,"played_version":33,"date":"2026-05-30T13:04:30+00:00"},{"song_id":552,"diff":3,"lamp":3,"ex_score":0,"played_version":33,"date":"2026-05-30T13:04:30+00:00"},{"song_id":572,"diff":3,"lamp":3,"ex_score":0,"played_version":33,"date":"2026-05-30T13:04:30+00:00"},{"song_id":578,"diff":2,"lamp":3,"ex_score":0,"played_version":33,"date":"2026-05-30T13:04:30+00:00"},{"song_id":578,"diff":3,"lamp":3,"ex_score":0,"played_version":33,"date":"2026-05-30T13:04:30+00:00"},{"song_id":585,"diff":3,"lamp":3,"ex_score":0,"played_version":33,"date":"2026-05-30T13:04:30+00:00"},{"song_id":591,"diff":3,"lamp":3,"ex_score":0,"played_version":33,"date":"2026-05-30T13:04:30+00:00"},{"song_id":602,"diff":3,"lamp":3,"ex_score":0,"played_version":33,"date":"2026-05-30T13:04:30+00:00"},{"song_id":603,"diff":3,"lamp":3,"ex_score":0,"played_version":33,"date":"2026-05-30T13:04:30+00:00"},{"song_id":604,"diff":3,"lamp":4,"ex_score":0,"played_version":33,"date":"2026-05-30T13:04:30+00:00"},{"song_id":616,"diff":3,"lamp":3,"ex_score":0,"played_version":33,"date":"2026-05-30T13:04:30+00:00"},{"song_id":622,"diff":3,"lamp":7,"ex_score":0,"played_version":33,"date":"2026-05-30T13:04:30+00:00"},{"song_id":627,"diff":3,"lamp":3,"ex_score":0,"played_version":33,"date":"2026-05-30T13:04:30+00:00"},{"song_id":628,"diff":3,"lamp":3,"ex_score":0,"played_version":33,"date":"2026-05-30T13:04:30+00:00"},{"song_id":636,"diff":3,"lamp":3,"ex_score":0,"played_version":33,"date":"2026-05-30T13:04:30+00:00"},{"song_id":645,"diff":3,"lamp":3,"ex_score":0,"played_version":33,"date":"2026-05-30T13:04:30+00:00"},{"song_id":649,"diff":3,"lamp":3,"ex_score":0,"played_version":33,"date":"2026-05-30T13:04:30+00:00"},{"song_id":650,"diff":3,"lamp":1,"ex_score":0,"played_version":33,"date":"2026-05-30T13:04:30+00:00"},{"song_id":660,"diff":3,"lamp":3,"ex_score":0,"played_version":33,"date":"2026-05-30T13:04:30+00:00"},{"song_id":661,"diff":3,"lamp":3,"ex_score":0,"played_version":33,"date":"2026-05-30T13:04:30+00:00"},{"song_id":671,"diff":3,"lamp":3,"ex_score":0,"played_version":33,"date":"2026-05-30T13:04:30+00:00"},{"song_id":673,"diff":3,"lamp":3,"ex_score":0,"played_version":33,"date":"2026-05-30T13:04:30+00:00"},{"song_id":680,"diff":3,"lamp":3,"ex_score":0,"played_version":33,"date":"2026-05-30T13:04:30+00:00"},{"song_id":694,"diff":3,"lamp":3,"ex_score":0,"played_version":33,"date":"2026-05-30T13:04:30+00:00"},{"song_id":696,"diff":3,"lamp":3,"ex_score":0,"played_version":33,"date":"2026-05-30T13:04:30+00:00"},{"song_id":700,"diff":3,"lamp":3,"ex_score":0,"played_version":33,"date":"2026-05-30T13:04:30+00:00"},{"song_id":702,"diff":3,"lamp":3,"ex_score":0,"played_version":33,"date":"2026-05-30T13:04:30+00:00"},{"song_id":713,"diff":3,"lamp":3,"ex_score":0,"played_version":33,"date":"2026-05-30T13:04:30+00:00"},{"song_id":720,"diff":3,"lamp":3,"ex_score":0,"played_version":33,"date":"2026-05-30T13:04:30+00:00"},{"song_id":721,"diff":3,"lamp":3,"ex_score":0,"played_version":33,"date":"2026-05-30T13:04:30+00:00"},{"song_id":723,"diff":3,"lamp":3,"ex_score":0,"played_version":33,"date":"2026-05-30T13:04:30+00:00"},{"song_id":727,"diff":3,"lamp":3,"ex_score":0,"played_version":33,"date":"2026-05-30T13:04:30+00:00"},{"song_id":731,"diff":3,"lamp":3,"ex_score":0,"played_version":33,"date":"2026-05-30T13:04:30+00:00"},{"song_id":744,"diff":3,"lamp":3,"ex_score":0,"played_version":33,"date":"2026-05-30T13:04:30+00:00"},{"song_id":754,"diff":3,"lamp":3,"ex_score":0,"played_version":33,"date":"2026-05-30T13:04:30+00:00"},{"song_id":764,"diff":3,"lamp":3,"ex_score":0,"played_version":33,"date":"2026-05-30T13:04:30+00:00"},{"song_id":778,"diff":3,"lamp":3,"ex_score":0,"played_version":33,"date":"2026-05-30T13:04:30+00:00"},{"song_id":779,"diff":3,"lamp":3,"ex_score":0,"played_version":33,"date":"2026-05-30T13:04:30+00:00"},{"song_id":781,"diff":3,"lamp":3,"ex_score":0,"played_version":33,"date":"2026-05-30T13:04:30+00:00"},{"song_id":788,"diff":3,"lamp":3,"ex_score":0,"played_version":33,"date":"2026-05-30T13:04:30+00:00"},{"song_id":794,"diff":3,"lamp":3,"ex_score":0,"played_version":33,"date":"2026-05-30T13:04:30+00:00"},{"song_id":798,"diff":3,"lamp":3,"ex_score":0,"played_version":33,"date":"2026-05-30T13:04:30+00:00"},{"song_id":800,"diff":3,"lamp":3,"ex_score":0,"played_version":33,"date":"2026-05-30T13:04:30+00:00"},{"song_id":806,"diff":3,"lamp":3,"ex_score":0,"played_version":33,"date":"2026-05-30T13:04:30+00:00"},{"song_id":808,"diff":3,"lamp":3,"ex_score":0,"played_version":33,"date":"2026-05-30T13:04:30+00:00"},{"song_id":815,"diff":3,"lamp":3,"ex_score":0,"played_version":33,"date":"2026-05-30T13:04:30+00:00"},{"song_id":826,"diff":3,"lamp":3,"ex_score":0,"played_version":33,"date":"2026-05-30T13:04:30+00:00"},{"song_id":830,"diff":3,"lamp":3,"ex_score":0,"played_version":33,"date":"2026-05-30T13:04:30+00:00"},{"song_id":835,"diff":3,"lamp":5,"ex_score":0,"played_version":33,"date":"2026-05-30T13:04:30+00:00"},{"song_id":848,"diff":3,"lamp":3,"ex_score":0,"played_version":33,"date":"2026-05-30T13:04:30+00:00"},{"song_id":858,"diff":3,"lamp":1,"ex_score":0,"played_version":33,"date":"2026-05-30T13:04:30+00:00"},{"song_id":868,"diff":3,"lamp":3,"ex_score":0,"played_version":33,"date":"2026-05-30T13:04:30+00:00"},{"song_id":873,"diff":3,"lamp":3,"ex_score":0,"played_version":33,"date":"2026-05-30T13:04:30+00:00"},{"song_id":876,"diff":3,"lamp":3,"ex_score":0,"played_version":33,"date":"2026-05-30T13:04:30+00:00"},{"song_id":879,"diff":3,"lamp":3,"ex_score":0,"played_version":33,"date":"2026-05-30T13:04:30+00:00"},{"song_id":883,"diff":3,"lamp":3,"ex_score":0,"played_version":33,"date":"2026-05-30T13:04:30+00:00"},{"song_id":884,"diff":3,"lamp":3,"ex_score":0,"played_version":33,"date":"2026-05-30T13:04:30+00:00"},{"song_id":885,"diff":3,"lamp":3,"ex_score":0,"played_version":33,"date":"2026-05-30T13:04:30+00:00"},{"song_id":887,"diff":3,"lamp":3,"ex_score":0,"played_version":33,"date":"2026-05-30T13:04:30+00:00"},{"song_id":889,"diff":3,"lamp":3,"ex_score":0,"played_version":33,"date":"2026-05-30T13:04:30+00:00"},{"song_id":896,"diff":3,"lamp":3,"ex_score":0,"played_version":33,"date":"2026-05-30T13:04:30+00:00"},{"song_id":911,"diff":3,"lamp":5,"ex_score":0,"played_version":33,"date":"2026-05-30T13:04:30+00:00"},{"song_id":912,"diff":3,"lamp":3,"ex_score":0,"played_version":33,"date":"2026-05-30T13:04:30+00:00"},{"song_id":917,"diff":3,"lamp":1,"ex_score":0,"played_version":33,"date":"2026-05-30T13:04:30+00:00"},{"song_id":928,"diff":3,"lamp":4,"ex_score":0,"played_version":33,"date":"2026-05-30T13:04:30+00:00"},{"song_id":947,"diff":3,"lamp":3,"ex_score":0,"played_version":33,"date":"2026-05-30T13:04:30+00:00"},{"song_id":949,"diff":3,"lamp":5,"ex_score":0,"played_version":33,"date":"2026-05-30T13:04:30+00:00"},{"song_id":959,"diff":3,"lamp":3,"ex_score":0,"played_version":33,"date":"2026-05-30T13:04:30+00:00"},{"song_id":961,"diff":3,"lamp":3,"ex_score":0,"played_version":33,"date":"2026-05-30T13:04:30+00:00"},{"song_id":962,"diff":3,"lamp":3,"ex_score":0,"played_version":33,"date":"2026-05-30T13:04:30+00:00"},{"song_id":965,"diff":3,"lamp":3,"ex_score":0,"played_version":33,"date":"2026-05-30T13:04:30+00:00"},{"song_id":979,"diff":3,"lamp":3,"ex_score":0,"played_version":33,"date":"2026-05-30T13:04:30+00:00"},{"song_id":981,"diff":3,"lamp":3,"ex_score":0,"played_version":33,"date":"2026-05-30T13:04:30+00:00"},{"song_id":983,"diff":3,"lamp":4,"ex_score":0,"played_version":33,"date":"2026-05-30T13:04:30+00:00"},{"song_id":1008,"diff":3,"lamp":3,"ex_score":0,"played_version":33,"date":"2026-05-30T13:04:30+00:00"},{"song_id":1104,"diff":3,"lamp":1,"ex_score":0,"played_version":33,"date":"2026-05-30T13:04:30+00:00"},{"song_id":1118,"diff":3,"lamp":2,"ex_score":0,"played_version":33,"date":"2026-05-30T13:04:30+00:00"},{"song_id":1423,"diff":2,"lamp":2,"ex_score":0,"played_version":33,"date":"2026-05-30T13:04:30+00:00"}],"sp":[]}